{"name":"Bdma.GitHub.io","tagline":"响应式重构说明","body":"### 稻草人首页 响应化\r\n在学bootstrap，又闲来无事就拿稻草人首页来试手了，总的原则是修旧如旧，像素级拷贝。<br>\r\n\r\n响应化简单来说就是在不同尺寸显示器下对应不同显示，对移动端支持更友好,都是代码猴，我就不细说了，发几张图给来到此处的非专业同学。<br>\r\n![iphone6](/img/iphone6.png) ![iphone6](/img/iphone6-menu.png)<br>\r\n手机（iphone6）访问时的样子<br>\r\n\r\n\r\n![iphone6](/img/ipad mini.png)<br>\r\n平板（ipad mini）访问时的样子<br>\r\n\r\n当然如果你在电脑端，先给个链接<http://bdma.github.io/54traveler.html>,<br>\r\n再上个贴心的二维码，手机扫一下就ok了。<br>\r\n![QR code](/img/54.png)<br>\r\n\r\n\r\n我初学\r\n我注意到","google":"","note":"Don't delete this file! It's used internally to help with page regeneration."}